CHANGES.txt
LICENSE.txt
MANIFEST.in
README.txt
bootstrap.py
ez_setup.py
setup.py
src/httprpclib.py
src/httprpclib.egg-info/PKG-INFO
src/httprpclib.egg-info/SOURCES.txt
src/httprpclib.egg-info/dependency_links.txt
src/httprpclib.egg-info/top_level.txt
test/reviewboard.cfg
test/test.py