Metadata-Version: 1.0
Name: httprpclib
Version: 0.1.1
Summary: A library that eases the use of RESTful web services
Home-page: http://zhirsch.name/code/?p=httprpclib.git;a=summary
Author: Zachary Hirsch
Author-email: zhirsch@umich.edu
License: BSD
Platform: UNKNOWN
Classifier: Development Status :: 3 - Alpha
Classifier: Environment :: Console
Classifier: Environment :: Web Environment
Classifier: Intended Audience :: Developers
Classifier: License :: OSI Approved :: BSD License
Classifier: Natural Language :: English
Classifier: Operating System :: OS Independent
Classifier: Programming Language :: Python :: 2.5
Classifier: Programming Language :: Python :: 2.6
Classifier: Programming Language :: Python :: 2.7
Classifier: Topic :: Internet :: WWW/HTTP
Classifier: Topic :: Software Development :: Libraries :: Python Modules
